mypydll/__init__.py
mypydll/func.py
pydll-1.1.0.dist-info/LICENSE
pydll-1.1.0.dist-info/METADATA
pydll-1.1.0.dist-info/WHEEL
pydll-1.1.0.dist-info/top_level.txt
pydll-1.1.0.dist-info/RECORD
