Metadata-Version: 2.1
Name: pydll
Version: 1.1.0
Summary: A expansion for me
Home-page: https://pypi.org/manage/project/MyPymods/
Author: GuangYao Sun
Author-email: 3150237154@qq.com
License: UNKNOWN
Platform: UNKNOWN
Classifier: Programming Language :: Python :: 3
Classifier: License :: OSI Approved :: MIT License
Classifier: Operating System :: OS Independent
Requires-Python: >=3.6
